{
  "items": [
    {
      "logoURL": "https://raw.githubusercontent.com/diksha-giri013/TDC-Listing/master/res/logo/incubator/ciba.jpg",
      "title": "CIBA",
      "industry": "IT, Food Processing, Clean Technology, Iot",
      "location": "Mumbai, Goa",
      "ticket-size":"--",
      "fb-url":"https://www.facebook.com/GoaCIBA/",
      "ln-url":"https://www.linkedin.com/company/centre-for-incubation-&-business-acceleration/",
      "website": "http://ciba.org.in/mumbai/"
    },
    {
      "logoURL": "https://raw.githubusercontent.com/diksha-giri013/TDC-Listing/master/res/logo/incubator/angelprime.png",
      "title": "Prime Venture Partners",
      "industry": "Mobile internet, ecommerce",
      "location": "Bengaluru",
      "ticket-size":"$200K-600K",
      "fb-url":"https://www.facebook.com/PrimeVenturePartners",
      "ln-url":"https://www.linkedin.com/company/angelprime",
      "website": "www.primevp.in"
    },
    {
      "logoURL": "https://raw.githubusercontent.com/diksha-giri013/TDC-Listing/master/res/logo/incubator/ciie.png",
      "title": "CIIE",
      "industry": "Information Communication Technology, Cleantech and Social",
      "location": "Ahmedabad",
      "ticket-size":"INR 20L",
      "fb-url":"https://www.facebook.com/CIIEIndia/",
      "ln-url":"https://www.linkedin.com/company/ciieindia/",
      "website": "www.ciie.co"
    },
    {
      "logoURL": "https://raw.githubusercontent.com/diksha-giri013/TDC-Listing/master/res/logo/incubator/seedfund.png",
      "title": "Seedfund",
      "industry": " Consumer Internet, Ecommerce, Education, Analytics",
      "location": "Mumbai",
      "ticket-size":"INR 1Cr-1.5Cr",
      "fb-url":"https://www.facebook.com/seedfund",
      "ln-url":"http://www.linkedin.com/groups/Seedfund-4088418?gid=4088418&trk=hb_side_g",
      "website": "www.seedfund.in"
    },   
    {
      "logoURL": "https://raw.githubusercontent.com/diksha-giri013/TDC-Listing/master/res/logo/incubator/amity-logo.png",
      "title": "Amity Innovation Incubator",
      "industry": "Multifold",
      "location": "Noida",
      "ticket-size":"Upto INR 1Cr",
      "fb-url":"https://www.facebook.com/Innovation-Circle-100582500048559/",
      "ln-url":"https://www.linkedin.com/groups/3878894",
      "website": "www.amity.edu/aii"
    },
    {
      "logoURL": "https://raw.githubusercontent.com/diksha-giri013/TDC-Listing/master/res/logo/incubator/ian.jpg",
      "title": "IAN Incubator",
      "industry": "IT/ITES, Telecom, Mobile VAS, Gaming...",
      "location": "Delhi",
      "ticket-size":"--",
      "fb-url":"https://www.facebook.com/indianangelnetwork?ref=hl/",
      "ln-url":"https://www.linkedin.com/company/indian-angel-network",
      "website": "www.ian-fund.com"
    },
    {
      "logoURL": "https://github.com/diksha-giri013/TDC-Listing/blob/master/res/logo/incubator/icreate.jpeg?raw=true",
      "title": "iCreate",
      "industry": "N/A",
      "location": "Ahmedabad",
      "ticket-size":"--",
      "fb-url":"https://www.facebook.com/icreateNextGen",
      "ln-url":"https://www.linkedin.com/in/icreatenextgen",
      "website": "icreate.org.in"
    },
    {
      "logoURL": "https://raw.githubusercontent.com/diksha-giri013/TDC-Listing/master/res/logo/incubator/indiavest.png",
      "title": "Indavest",
      "industry": "Ecommerce, Mobile Applications, Software",
      "location": "Bengaluru",
      "ticket-size":"--",
      "fb-url":"#",
      "ln-url":"https://www.linkedin.com/company/indavest-ventures/about/",
      "website": "www.indavest.com"
    },
    {
      "logoURL": "https://raw.githubusercontent.com/diksha-giri013/TDC-Listing/master/res/logo/incubator/khosla-labs.png",
      "title": "Khosla Labs",
      "industry": "Big Data, Mobile payment & banking, Healthcare",
      "location": "Bengaluru",
      "ticket-size":"--",
      "fb-url":"http://facebook.com/khoslalabs",
      "ln-url":"https://www.linkedin.com/company/khosla-labs?originalSubdomain=in",
      "website": "khoslalabs.com/"
    },
    {
      "logoURL": "https://raw.githubusercontent.com/diksha-giri013/TDC-Listing/master/res/logo/incubator/ndbi.png",
      "title": "NDBI",
      "industry": "Medical Technology, Agri, Bio",
      "location": "Bengaluru",
      "ticket-size":"--",
      "fb-url":"https://www.facebook.com/NDBI-Bengaluru-183444818814714/?__tn__=%2Cd%2CP-R&eid=ARBzoF-4XmRMUzLqVl7NP3Vx3i3-ToFrXgH_Y3r6XDEzP9dpGnaN_horXKO0FeurKGSA8IlOwKUs8p07",
      "ln-url":"#",
      "website": "www.ndbiindia.org"
    },
    {
      "logoURL": "https://raw.githubusercontent.com/diksha-giri013/TDC-Listing/master/res/logo/incubator/MUTBI.png",
      "title": "MUTBI",
      "industry": "Consumer commerce, education, design",
      "location": "Manipal",
      "ticket-size":"--",
      "fb-url":"#",
      "ln-url":"https://www.linkedin.com/in/mutbi/",
      "website": "www.mutbimanipal.org"
    },
    {
      "logoURL": "https://raw.githubusercontent.com/diksha-giri013/TDC-Listing/master/res/logo/incubator/villgro.jpg",
      "title": "Villgro",
      "industry": "Social enterprises",
      "location": "Chennai",
      "ticket-size":"INR 50L",
      "fb-url":"https://www.facebook.com/villgro",
      "ln-url":"https://www.linkedin.com/company/villgro-innovations-foundation",
      "website": "www.villgro.org"
    },
    {
      "logoURL": "https://raw.githubusercontent.com/diksha-giri013/TDC-Listing/master/res/logo/incubator/venture-centre.png",
      "title": "Venture Center",
      "industry": "Consumer commerce, education, design",
      "location": "Pune",
      "ticket-size":"INR 1L-25L",
      "fb-url":"https://www.facebook.com/venturecenterpune",
      "ln-url":"https://www.linkedin.com/in/venture-center-pune/",
      "website": "www.venturecenter.co.in"
    },
    {
      "logoURL": "https://raw.githubusercontent.com/diksha-giri013/TDC-Listing/master/res/logo/incubator/sandbox.jpg",
      "title": "FSI",
      "industry": "Multisector, Social Enterprises",
      "location": "Hubli",
      "ticket-size":"--",
      "fb-url":"https://www.facebook.com/Thesandboxincubator/",
      "ln-url":"https://www.linkedin.com/company/sandbox-startups-incubator/",
      "website": "www.sandboxstartups.org"
    },
    {
      "logoURL": "https://raw.githubusercontent.com/diksha-giri013/TDC-Listing/master/res/logo/incubator/IIITD.png",
      "title": "IIITD IIC",
      "industry": "Multisector",
      "location": "New Delhi",
      "ticket-size":"--",
      "fb-url":"https://www.facebook.com/I3C.IIITD/",
      "ln-url":"https://www.linkedin.com/company/iiitd-innovation-and-incubation-center/?originalSubdomain=in",
      "website": "www.iiitd.ac.in"
    }
  ]
}